scietex/logging/__init__.py
scietex/logging/basic_handler.py
scietex/logging/formatter.py
scietex/logging/message_broker_handler.py
scietex/logging/py.typed
scietex/logging/redis_handler.py
scietex/logging/valkey_handler.py
scietex_logging-0.1.1.dist-info/licenses/LICENSE
scietex_logging-0.1.1.dist-info/METADATA
scietex_logging-0.1.1.dist-info/WHEEL
scietex_logging-0.1.1.dist-info/top_level.txt
scietex_logging-0.1.1.dist-info/RECORD
