Metadata-Version: 2.4
Name: scietex.logging
Version: 0.1.1
Summary: Asyncio logging handlers
Author-email: Anton Bondarenko <bond.anton@gmail.com>
License: MIT License
Project-URL: Homepage, https://github.com/bond-anton/scietex.logging
Project-URL: Bug Tracker, https://github.com/bond-anton/scietex.logging/issues
Classifier: Programming Language :: Python :: 3
Classifier: License :: OSI Approved :: MIT License
Classifier: Operating System :: OS Independent
Requires-Python: >=3.9
License-File: LICENSE
Provides-Extra: redis
Requires-Dist: redis>=4.2.0; extra == "redis"
Provides-Extra: valkey
Requires-Dist: valkey-glide~=2.0.0; extra == "valkey"
Provides-Extra: all
Requires-Dist: redis>=4.2.0; extra == "all"
Requires-Dist: valkey-glide~=2.0.0; extra == "all"
Provides-Extra: test
Requires-Dist: flake8; extra == "test"
Requires-Dist: pytest; extra == "test"
Requires-Dist: pytest-asyncio; extra == "test"
Provides-Extra: lint
Requires-Dist: pylint; extra == "lint"
Dynamic: license-file
